bible/__init__.py
bible/bible.py
bible/data.py
bible_passage_reference_parser-1.0.4.dist-info/METADATA
bible_passage_reference_parser-1.0.4.dist-info/WHEEL
bible_passage_reference_parser-1.0.4.dist-info/top_level.txt
bible_passage_reference_parser-1.0.4.dist-info/RECORD
