Metadata-Version: 2.1
Name: bible-passage-reference-parser
Version: 1.0.4
Summary: Bible reference classes
Home-page: http://gitlab.com/rseal/bible-passage-reference-parser-python
Author: Ryan Seal
Author-email: rseal@twr.org
License: UNKNOWN
Keywords: encoding,i18n,xml,bible,django
Platform: UNKNOWN
Classifier: Programming Language :: Python
Classifier: Programming Language :: Python :: 2.6
Classifier: Programming Language :: Python :: 2.7
Classifier: Programming Language :: Python :: 3
Classifier: Programming Language :: Python :: 3.6
Classifier: Framework :: Django
Classifier: Development Status :: 5 - Production/Stable
Classifier: Environment :: Other Environment
Classifier: Intended Audience :: Developers
Classifier: License :: OSI Approved :: BSD License
Classifier: Operating System :: OS Independent
Classifier: Topic :: Religion
Classifier: Topic :: Software Development :: Libraries :: Python Modules
